minitorch/__init__.py
minitorch/minitorch.py
minitorch-0.5.2.dist-info/licenses/LICENSE
minitorch-0.5.2.dist-info/METADATA
minitorch-0.5.2.dist-info/WHEEL
minitorch-0.5.2.dist-info/top_level.txt
minitorch-0.5.2.dist-info/RECORD
