Metadata-Version: 2.4
Name: minitorch
Version: 0.5.2
Summary: Lightweight deep learning library with autograd and neural network layers.
Home-page: https://github.com/yourusername/minitorch
Author: iyaz
Author-email: Your Name <your.email@example.com>
Classifier: Programming Language :: Python :: 3
Classifier: License :: OSI Approved :: MIT License
Classifier: Operating System :: OS Independent
Requires-Python: >=3.6
License-File: LICENSE
Requires-Dist: numpy
Dynamic: author
Dynamic: home-page
Dynamic: license-file
Dynamic: requires-python
